{
  "packId": "keiyoushi-core-expanded",
  "displayName": "Keiyoushi Expanded Core Source Pack",
  "sourceCount": 431,
  "familyCounts": {
    "ComiciViewerAlt": 11,
    "HttpSource": 2,
    "Iken": 8,
    "Keyoapp": 19,
    "LectorMoe": 14,
    "MadTheme": 20,
    "Madara": 220,
    "MangaBox": 2,
    "MangaCatalog": 14,
    "MangaHub": 11,
    "MangaThemesia": 102,
    "PizzaReader": 8
  },
  "languageCounts": {
    "all": 14,
    "ar": 21,
    "cs": 1,
    "en": 209,
    "es": 45,
    "fr": 20,
    "id": 27,
    "it": 5,
    "ja": 11,
    "ko": 1,
    "pl": 1,
    "pt": 3,
    "ru": 1,
    "th": 25,
    "tr": 44,
    "vi": 3
  },
  "nsfwCount": 240,
  "appStoreSafe": true,
  "containsExecutableCode": false,
  "requiresExternalBridge": false,
  "sourcePackPath": "tmp/yomira-source-packs/keiyoushi-core-expanded/source-pack.json",
  "validationState": "Valid",
  "installableCount": 431,
  "blockedCount": 0,
  "rejectedCount": 0,
  "warningCount": 0,
  "errorCount": 0,
  "importDryRun": true
}